fetchnb/__init__.py
fetchnb-0.1.0.dist-info/METADATA
fetchnb-0.1.0.dist-info/WHEEL
fetchnb-0.1.0.dist-info/top_level.txt
fetchnb-0.1.0.dist-info/RECORD
