Metadata-Version: 2.4
Name: fetchnb
Version: 0.1.0
Summary: Fetch code from dontpad.com and write it into a Jupyter Notebook
Home-page: https://github.com/vikas-bhat-d/fetchnb
Author: Vikas Bhat D
Author-email: vikasdbhat@gmail.com
Classifier: Programming Language :: Python :: 3
Classifier: License :: OSI Approved :: MIT License
Classifier: Operating System :: OS Independent
Requires-Python: >=3.6
Requires-Dist: requests
Requires-Dist: nbformat
Dynamic: author
Dynamic: author-email
Dynamic: classifier
Dynamic: description
Dynamic: description-content-type
Dynamic: home-page
Dynamic: requires-dist
Dynamic: requires-python
Dynamic: summary
